LICENSE
MANIFEST.in
README.md
setup.cfg
setup.py
sabertooth/__init__.py
sabertooth/cli.py
sabertooth/subapi.py
sabertooth.egg-info/PKG-INFO
sabertooth.egg-info/SOURCES.txt
sabertooth.egg-info/dependency_links.txt
sabertooth.egg-info/entry_points.txt
sabertooth.egg-info/pbr.json
sabertooth.egg-info/top_level.txt
sabertooth/providers/__init__.py
sabertooth/providers/opensubtitles.py
tests/__init__.py