Metadata-Version: 1.1
Name: sabertooth
Version: 0.3.2
Summary: An OpenSubtitles Client
Home-page: https://github.com/walidsa3d/sabertooth
Author: Walid Saad
Author-email: walid.sa3d@gmail.com
License: MIT
Keywords: cli subtitles opensuhbtitles
Platform: UNKNOWN
Classifier: Development Status :: 4 - Beta
Classifier: Environment :: Console
Classifier: Intended Audience :: End Users/Desktop
Classifier: Operating System :: OS Independent
Classifier: Natural Language :: English
Classifier: Programming Language :: Python :: 2
Classifier: Topic :: Multimedia :: Video
Classifier: Topic :: Utilities
